eof/__init__.py
eof/__main__.py
eof/_asf_s3.py
eof/_auth.py
eof/_select_orbit.py
eof/_types.py
eof/asf_client.py
eof/cli.py
eof/dataspace_client.py
eof/download.py
eof/log.py
eof/parsing.py
eof/products.py
eof/tests/__init__.py
eof/tests/test_asf_client.py
eof/tests/test_asf_s3.py
eof/tests/test_dataspace_client.py
eof/tests/test_eof.py
eof/tests/test_products.py
sentineleof-0.11.1.dist-info/licenses/LICENSE.txt
sentineleof-0.11.1.dist-info/METADATA
sentineleof-0.11.1.dist-info/WHEEL
sentineleof-0.11.1.dist-info/entry_points.txt
sentineleof-0.11.1.dist-info/top_level.txt
sentineleof-0.11.1.dist-info/RECORD
