Metadata-Version: 2.4
Name: sentineleof
Version: 0.11.1
Summary: Download precise orbit files for Sentinel 1 products
Home-page: https://github.com/scottstanie/sentineleof
Author: Scott Staniewicz
Author-email: scott.stanie@gmail.com
Classifier: Programming Language :: Python
Classifier: Programming Language :: Python :: 3.9
Classifier: Programming Language :: Python :: 3.10
Classifier: Programming Language :: Python :: 3.11
Classifier: Programming Language :: Python :: 3.12
Classifier: Programming Language :: Python :: 3.13
Classifier: License :: OSI Approved :: MIT License
Classifier: Topic :: Scientific/Engineering
Classifier: Intended Audience :: Science/Research
License-File: LICENSE.txt
Requires-Dist: requests
Requires-Dist: click
Requires-Dist: python-dateutil
Dynamic: author
Dynamic: author-email
Dynamic: classifier
Dynamic: description
Dynamic: description-content-type
Dynamic: home-page
Dynamic: license-file
Dynamic: requires-dist
Dynamic: summary
